[
  {
    "id": "azjn3k7w1",
    "username": "pp@pp.com",
    "email": "pp@pp.com",
    "password": "123",
    "roles": [
      "Group Admin"
    ],
    "groups": []
  },
  {
    "id": "si8w9m6m7",
    "username": "super",
    "email": "super",
    "password": "123",
    "roles": [
      "Super Admin"
    ],
    "groups": [
      {
        "id": "vtybsprwr",
        "name": "123",
        "description": "1233",
        "createdBy": "si8w9m6m7",
        "channels": [],
        "imageUrl": ""
      }
    ]
  },
  {
    "id": "gky27a7pi",
    "username": "ff@ff.com",
    "email": "ff@ff.com",
    "password": "123",
    "roles": [
      "Group Admin"
    ],
    "groups": [
      {
        "id": "c7enyp2eu",
        "name": "f3",
        "description": "33",
        "createdBy": "gky27a7pi",
        "channels": [],
        "imageUrl": ""
      },
      {
        "id": "b5vs5zaso",
        "name": "f11",
        "description": "11",
        "createdBy": "gky27a7pi",
        "channels": [],
        "imageUrl": ""
      },
      {
        "id": "u9hchkhxz",
        "name": "f12",
        "description": "12",
        "createdBy": "gky27a7pi",
        "channels": [
          {
            "id": "xexuxz437",
            "name": "f12.1",
            "description": "12.1"
          },
          {
            "id": "ybbzs080m",
            "name": "f13.1",
            "description": "13"
          }
        ],
        "imageUrl": ""
      },
      {
        "id": "jiz302ga4",
        "name": "f14",
        "description": "",
        "createdBy": "gky27a7pi",
        "channels": [
          {
            "id": "hz6jh4xsn",
            "name": "14.1",
            "description": "14.1"
          },
          {
            "id": "svyj9rho4",
            "name": "14.2",
            "description": "14.2"
          }
        ],
        "imageUrl": ""
      },
      {
        "id": "qc5vl3ozb",
        "name": "f16",
        "description": "16",
        "createdBy": "gky27a7pi",
        "channels": [
          {
            "id": "9xpbogmzl",
            "name": "16-1",
            "description": ""
          }
        ],
        "imageUrl": ""
      }
    ]
  },
  {
    "id": "ff6qzxdfz",
    "username": "hh@hh.com",
    "email": "hh@hh.com",
    "password": "123",
    "roles": [
      "Group Admin"
    ],
    "groups": []
  },
  {
    "id": "amd7zzbre",
    "username": "ww@ww.com",
    "email": "ww@ww.com",
    "password": "123",
    "roles": [
      "User"
    ],
    "groups": []
  },
  {
    "id": "j8qwpib05",
    "username": "yy@yy.com",
    "email": "yy@yy.com",
    "password": "123",
    "roles": [
      "User"
    ],
    "groups": []
  },
  {
    "id": "fes6psyln",
    "username": "kk@kk.com",
    "email": "kk@kk.com",
    "password": "123",
    "roles": [
      "User"
    ],
    "groups": []
  },
  {
    "id": "0pr18t8vp",
    "username": "t4@t4.com",
    "email": "t4@t4.com",
    "password": "123",
    "roles": [
      "User"
    ],
    "groups": [],
    "interestGroups": [],
    "_id": "67069245d0d1ae725d5a6c13"
  }
]